aiotrino/__init__.py
aiotrino/_version.py
aiotrino/auth.py
aiotrino/client.py
aiotrino/constants.py
aiotrino/dbapi.py
aiotrino/exceptions.py
aiotrino/logging.py
aiotrino/mapper.py
aiotrino/transaction.py
aiotrino/types.py
aiotrino/utils.py
aiotrino/sqlalchemy/__init__.py
aiotrino/sqlalchemy/compiler.py
aiotrino/sqlalchemy/datatype.py
aiotrino/sqlalchemy/dialect.py
aiotrino/sqlalchemy/error.py
aiotrino/sqlalchemy/util.py
aiotrino_patched-0.3.1.dist-info/METADATA
aiotrino_patched-0.3.1.dist-info/WHEEL
aiotrino_patched-0.3.1.dist-info/entry_points.txt
aiotrino_patched-0.3.1.dist-info/licenses/LICENSE
aiotrino_patched-0.3.1.dist-info/RECORD
