Metadata-Version: 2.4
Name: aiotrino-patched
Version: 0.3.1
Summary: Asyncio client for the Trino distributed SQL Engine
Project-URL: Homepage, https://github.com/gledi-ai/aiotrino
Project-URL: Repository, https://github.com/gledi-ai/aiotrino
Project-URL: Documentation, https://github.com/gledi-ai/aiotrino
Author-email: Michiel van der Lee & Trino Team <jmt.vanderlee@gmail.com>
License-Expression: Apache-2.0
License-File: LICENSE
Keywords: asyncio,database,sql,trino
Classifier: Development Status :: 4 - Beta
Classifier: Intended Audience :: Developers
Classifier: License :: OSI Approved :: Apache Software License
Classifier: Operating System :: MacOS :: MacOS X
Classifier: Operating System :: Microsoft :: Windows
Classifier: Operating System :: POSIX
Classifier: Programming Language :: Python
Classifier: Programming Language :: Python :: 3
Classifier: Programming Language :: Python :: 3.12
Classifier: Programming Language :: Python :: 3.13
Classifier: Programming Language :: Python :: 3.14
Classifier: Programming Language :: Python :: Implementation :: CPython
Classifier: Programming Language :: Python :: Implementation :: PyPy
Classifier: Topic :: Database :: Front-Ends
Requires-Python: <4,>=3.12
Requires-Dist: aiohttp
Requires-Dist: aioitertools
Requires-Dist: lz4
Requires-Dist: python-dateutil
Requires-Dist: pytz
Requires-Dist: tzdata
Requires-Dist: tzlocal
Requires-Dist: zstandard
Provides-Extra: all
Requires-Dist: sqlalchemy>=2.0; extra == 'all'
Provides-Extra: sqlalchemy
Requires-Dist: sqlalchemy>=2.0; extra == 'sqlalchemy'
